shock/__init__.py
shock/constants.py
shock/shock_connect.py
shock/shock_echo.py
shock/six.py
shock/utils.py
shock-0.2.4.data/scripts/shock
shock-0.2.4.dist-info/METADATA
shock-0.2.4.dist-info/WHEEL
shock-0.2.4.dist-info/top_level.txt
shock-0.2.4.dist-info/RECORD
