Metadata-Version: 2.1
Name: shock
Version: 0.2.4
Summary: tool for server load performance testing
Home-page: https://github.com/dantezhu/shock
Author: dantezhu
Author-email: dantezhu <zny2008@gmail.com>
License: BSD
Project-URL: Homepage, https://github.com/dantezhu/shock
Platform: any
Requires-Dist: netkit
Requires-Dist: click
Requires-Dist: setproctitle
